{
  "generated_at": "2026-04-01T12:55",
  "insights": [
    {
      "id": "A",
      "text": "A las 12h se están acumulando los retrasos — 7 trenes afectados",
      "severity": "warn",
      "meta": {
        "hour": 12
      }
    },
    {
      "id": "D",
      "text": "Históricamente los lunes son el día con más retrasos (media 1%); los miércoles son los más puntuales",
      "severity": "info"
    },
    {
      "id": "F",
      "text": "Entre las 00h y las 12h los retrasos son habitualmente bajos o inexistentes",
      "severity": "ok"
    }
  ]
}