{
  "station_id": "05655",
  "name": "Maliaño Vidriera",
  "generated_at": "2026-03-31T15:00:21+02:00",
  "arrivals": [
    {
      "trip_id": "6286M71217C3",
      "route_id": "62T0005C3",
      "train_name": "C3",
      "headsign": "La Cantábrica",
      "origin": "Santander",
      "scheduled_time": "15:01",
      "estimated_time": "15:01",
      "delay_min": 0.0,
      "status": "en_hora"
    },
    {
      "trip_id": "6286M71216C3",
      "route_id": "62T0006C3",
      "train_name": "C3",
      "headsign": "Santander",
      "origin": "La Cantábrica",
      "scheduled_time": "15:25",
      "estimated_time": "15:25",
      "delay_min": 0.0,
      "status": "en_hora"
    },
    {
      "trip_id": "6286M71369C3",
      "route_id": "62T0005C3",
      "train_name": "C3",
      "headsign": "Maliaño Vidriera",
      "origin": "Santander",
      "scheduled_time": "15:30",
      "estimated_time": "15:30",
      "delay_min": 0.0,
      "status": "en_hora"
    },
    {
      "trip_id": "6286M71304C3",
      "route_id": "62T0006C3",
      "train_name": "C3",
      "headsign": "Santander",
      "origin": "Astillero",
      "scheduled_time": "15:34",
      "estimated_time": "15:34",
      "delay_min": 0.0,
      "status": "en_hora"
    },
    {
      "trip_id": "6286M71366C3",
      "route_id": "62T0006C3",
      "train_name": "C3",
      "headsign": "Santander",
      "origin": "Astillero",
      "scheduled_time": "15:57",
      "estimated_time": "15:57",
      "delay_min": 0.0,
      "status": "en_hora"
    }
  ]
}