{
  "station_id": "18003",
  "name": "Méndez álvaro P.v.",
  "generated_at": "2026-04-02T11:55:12+02:00",
  "arrivals": [
    {
      "trip_id": "1088J75124C10",
      "route_id": "10T0003C10",
      "train_name": "C10",
      "headsign": "Madrid-Chamartín-Clara Campoamor",
      "origin": "Villalba De Guadarrama",
      "scheduled_time": "12:00",
      "estimated_time": "12:00",
      "delay_min": 0.0,
      "status": "en_hora"
    },
    {
      "trip_id": "1088J77029C5",
      "route_id": "10T0048C5",
      "train_name": "C5",
      "headsign": "Madrid-Atocha Cercanías",
      "origin": "Fuenlabrada",
      "scheduled_time": "12:03",
      "estimated_time": "12:03",
      "delay_min": 0.0,
      "status": "en_hora"
    },
    {
      "trip_id": "1088J75324C10",
      "route_id": "10T0076C10",
      "train_name": "C10",
      "headsign": "Pinar De Las Rozas",
      "origin": "Madrid-Chamartín-Clara Campoamor",
      "scheduled_time": "12:04",
      "estimated_time": "12:04",
      "delay_min": 0.0,
      "status": "en_hora"
    },
    {
      "trip_id": "1088J76720C5",
      "route_id": "10T0017C5",
      "train_name": "C5",
      "headsign": "Humanes",
      "origin": "Madrid-Atocha Cercanías",
      "scheduled_time": "12:04",
      "estimated_time": "12:04",
      "delay_min": 0.0,
      "status": "en_hora"
    },
    {
      "trip_id": "1088J76725C5",
      "route_id": "10T0018C5",
      "train_name": "C5",
      "headsign": "Madrid-Atocha Cercanías",
      "origin": "Humanes",
      "scheduled_time": "12:13",
      "estimated_time": "12:13",
      "delay_min": 0.0,
      "status": "en_hora"
    },
    {
      "trip_id": "1088J77028C5",
      "route_id": "10T0047C5",
      "train_name": "C5",
      "headsign": "Fuenlabrada",
      "origin": "Madrid-Atocha Cercanías",
      "scheduled_time": "12:14",
      "estimated_time": "12:14",
      "delay_min": 0.0,
      "status": "en_hora"
    },
    {
      "trip_id": "1088J75321C10",
      "route_id": "10T0075C10",
      "train_name": "C10",
      "headsign": "Madrid-Chamartín-Clara Campoamor",
      "origin": "Pinar De Las Rozas",
      "scheduled_time": "12:15",
      "estimated_time": "12:15",
      "delay_min": 0.0,
      "status": "en_hora"
    },
    {
      "trip_id": "1088J75224C10",
      "route_id": "10T0004C10",
      "train_name": "C10",
      "headsign": "Villalba De Guadarrama",
      "origin": "Madrid-Chamartín-Clara Campoamor",
      "scheduled_time": "12:19",
      "estimated_time": "12:19",
      "delay_min": 0.0,
      "status": "en_hora"
    },
    {
      "trip_id": "1088J77031C5",
      "route_id": "10T0048C5",
      "train_name": "C5",
      "headsign": "Madrid-Atocha Cercanías",
      "origin": "Fuenlabrada",
      "scheduled_time": "12:23",
      "estimated_time": "12:23",
      "delay_min": 0.0,
      "status": "en_hora"
    },
    {
      "trip_id": "1088J76722C5",
      "route_id": "10T0017C5",
      "train_name": "C5",
      "headsign": "Humanes",
      "origin": "Madrid-Atocha Cercanías",
      "scheduled_time": "12:24",
      "estimated_time": "12:24",
      "delay_min": 0.0,
      "status": "en_hora"
    },
    {
      "trip_id": "1088J75126C10",
      "route_id": "10T0003C10",
      "train_name": "C10",
      "headsign": "Madrid-Chamartín-Clara Campoamor",
      "origin": "Villalba De Guadarrama",
      "scheduled_time": "12:30",
      "estimated_time": "12:30",
      "delay_min": 0.0,
      "status": "en_hora"
    },
    {
      "trip_id": "1088J75326C10",
      "route_id": "10T0076C10",
      "train_name": "C10",
      "headsign": "Pinar De Las Rozas",
      "origin": "Madrid-Chamartín-Clara Campoamor",
      "scheduled_time": "12:32",
      "estimated_time": "12:32",
      "delay_min": 0.0,
      "status": "en_hora"
    },
    {
      "trip_id": "1088J76727C5",
      "route_id": "10T0018C5",
      "train_name": "C5",
      "headsign": "Madrid-Atocha Cercanías",
      "origin": "Humanes",
      "scheduled_time": "12:33",
      "estimated_time": "12:33",
      "delay_min": 0.0,
      "status": "en_hora"
    },
    {
      "trip_id": "1088J77030C5",
      "route_id": "10T0047C5",
      "train_name": "C5",
      "headsign": "Fuenlabrada",
      "origin": "Madrid-Atocha Cercanías",
      "scheduled_time": "12:34",
      "estimated_time": "12:34",
      "delay_min": 0.0,
      "status": "en_hora"
    },
    {
      "trip_id": "1088J77033C5",
      "route_id": "10T0048C5",
      "train_name": "C5",
      "headsign": "Madrid-Atocha Cercanías",
      "origin": "Fuenlabrada",
      "scheduled_time": "12:43",
      "estimated_time": "12:43",
      "delay_min": 0.0,
      "status": "en_hora"
    },
    {
      "trip_id": "1088J76724C5",
      "route_id": "10T0017C5",
      "train_name": "C5",
      "headsign": "Humanes",
      "origin": "Madrid-Atocha Cercanías",
      "scheduled_time": "12:44",
      "estimated_time": "12:44",
      "delay_min": 0.0,
      "status": "en_hora"
    },
    {
      "trip_id": "1088J75323C10",
      "route_id": "10T0075C10",
      "train_name": "C10",
      "headsign": "Madrid-Chamartín-Clara Campoamor",
      "origin": "Pinar De Las Rozas",
      "scheduled_time": "12:45",
      "estimated_time": "12:45",
      "delay_min": 0.0,
      "status": "en_hora"
    },
    {
      "trip_id": "1088J75226C10",
      "route_id": "10T0004C10",
      "train_name": "C10",
      "headsign": "Villalba De Guadarrama",
      "origin": "Madrid-Chamartín-Clara Campoamor",
      "scheduled_time": "12:49",
      "estimated_time": "12:49",
      "delay_min": 0.0,
      "status": "en_hora"
    },
    {
      "trip_id": "1088J76729C5",
      "route_id": "10T0018C5",
      "train_name": "C5",
      "headsign": "Madrid-Atocha Cercanías",
      "origin": "Humanes",
      "scheduled_time": "12:53",
      "estimated_time": "12:53",
      "delay_min": 0.0,
      "status": "en_hora"
    },
    {
      "trip_id": "1088J77032C5",
      "route_id": "10T0047C5",
      "train_name": "C5",
      "headsign": "Fuenlabrada",
      "origin": "Madrid-Atocha Cercanías",
      "scheduled_time": "12:54",
      "estimated_time": "12:54",
      "delay_min": 0.0,
      "status": "en_hora"
    }
  ]
}