{
  "station_id": "19001",
  "name": "Universidad Pontificia De Comillas",
  "generated_at": "2026-04-01T08:00:25+02:00",
  "arrivals": [
    {
      "trip_id": "1087X20234C4a",
      "route_id": "10T0013C4a",
      "train_name": "C4a",
      "headsign": "Parla",
      "origin": "Alcobendas-San Sebastián De Los Reyes",
      "scheduled_time": "08:01",
      "estimated_time": "08:01",
      "delay_min": 0.0,
      "status": "en_hora"
    },
    {
      "trip_id": "1087X20236C4a",
      "route_id": "10T0013C4a",
      "train_name": "C4a",
      "headsign": "Parla",
      "origin": "Alcobendas-San Sebastián De Los Reyes",
      "scheduled_time": "08:05",
      "estimated_time": "08:05",
      "delay_min": 0.0,
      "status": "en_hora"
    },
    {
      "trip_id": "1087X20225C4a",
      "route_id": "10T0014C4a",
      "train_name": "C4a",
      "headsign": "Alcobendas-San Sebastián De Los Reyes",
      "origin": "Parla",
      "scheduled_time": "08:10",
      "estimated_time": "08:10",
      "delay_min": 0.0,
      "status": "en_hora"
    },
    {
      "trip_id": "1087X20227C4a",
      "route_id": "10T0014C4a",
      "train_name": "C4a",
      "headsign": "Alcobendas-San Sebastián De Los Reyes",
      "origin": "Parla",
      "scheduled_time": "08:23",
      "estimated_time": "08:23",
      "delay_min": 0.0,
      "status": "en_hora"
    },
    {
      "trip_id": "1087X20238C4a",
      "route_id": "10T0013C4a",
      "train_name": "C4a",
      "headsign": "Parla",
      "origin": "Alcobendas-San Sebastián De Los Reyes",
      "scheduled_time": "08:23",
      "estimated_time": "08:23",
      "delay_min": 0.0,
      "status": "en_hora"
    },
    {
      "trip_id": "1087X20229C4a",
      "route_id": "10T0014C4a",
      "train_name": "C4a",
      "headsign": "Alcobendas-San Sebastián De Los Reyes",
      "origin": "Parla",
      "scheduled_time": "08:35",
      "estimated_time": "08:35",
      "delay_min": 0.0,
      "status": "en_hora"
    },
    {
      "trip_id": "1087X20240C4a",
      "route_id": "10T0013C4a",
      "train_name": "C4a",
      "headsign": "Parla",
      "origin": "Alcobendas-San Sebastián De Los Reyes",
      "scheduled_time": "08:37",
      "estimated_time": "08:37",
      "delay_min": 0.0,
      "status": "en_hora"
    },
    {
      "trip_id": "1087X20231C4a",
      "route_id": "10T0014C4a",
      "train_name": "C4a",
      "headsign": "Alcobendas-San Sebastián De Los Reyes",
      "origin": "Parla",
      "scheduled_time": "08:45",
      "estimated_time": "08:45",
      "delay_min": 0.0,
      "status": "en_hora"
    },
    {
      "trip_id": "1087X20242C4a",
      "route_id": "10T0013C4a",
      "train_name": "C4a",
      "headsign": "Madrid-Atocha Cercanías",
      "origin": "Alcobendas-San Sebastián De Los Reyes",
      "scheduled_time": "08:50",
      "estimated_time": "08:50",
      "delay_min": 0.0,
      "status": "en_hora"
    },
    {
      "trip_id": "1087X20233C4a",
      "route_id": "10T0014C4a",
      "train_name": "C4a",
      "headsign": "Alcobendas-San Sebastián De Los Reyes",
      "origin": "Parla",
      "scheduled_time": "08:59",
      "estimated_time": "08:59",
      "delay_min": 0.0,
      "status": "en_hora"
    },
    {
      "trip_id": "1087X20244C4a",
      "route_id": "10T0013C4a",
      "train_name": "C4a",
      "headsign": "Parla",
      "origin": "Alcobendas-San Sebastián De Los Reyes",
      "scheduled_time": "08:59",
      "estimated_time": "08:59",
      "delay_min": 0.0,
      "status": "en_hora"
    }
  ]
}