{
  "station_id": "35606",
  "name": "Móstoles",
  "generated_at": "2026-04-04T18:55:13+02:00",
  "arrivals": [
    {
      "trip_id": "1090S76499C5",
      "route_id": "10T0018C5",
      "train_name": "C5",
      "headsign": "Móstoles-El Soto",
      "origin": "Madrid-Atocha Cercanías",
      "scheduled_time": "19:01",
      "estimated_time": "19:01",
      "delay_min": 0.0,
      "status": "en_hora"
    },
    {
      "trip_id": "1090S76510C5",
      "route_id": "10T0017C5",
      "train_name": "C5",
      "headsign": "Madrid-Atocha Cercanías",
      "origin": "Móstoles-El Soto",
      "scheduled_time": "19:04",
      "estimated_time": "19:04",
      "delay_min": 0.0,
      "status": "en_hora"
    },
    {
      "trip_id": "1090S76501C5",
      "route_id": "10T0018C5",
      "train_name": "C5",
      "headsign": "Móstoles-El Soto",
      "origin": "Madrid-Atocha Cercanías",
      "scheduled_time": "19:11",
      "estimated_time": "19:11",
      "delay_min": 0.0,
      "status": "en_hora"
    },
    {
      "trip_id": "1090S76512C5",
      "route_id": "10T0017C5",
      "train_name": "C5",
      "headsign": "Madrid-Atocha Cercanías",
      "origin": "Móstoles-El Soto",
      "scheduled_time": "19:14",
      "estimated_time": "19:14",
      "delay_min": 0.0,
      "status": "en_hora"
    },
    {
      "trip_id": "1090S76503C5",
      "route_id": "10T0018C5",
      "train_name": "C5",
      "headsign": "Móstoles-El Soto",
      "origin": "Madrid-Atocha Cercanías",
      "scheduled_time": "19:21",
      "estimated_time": "19:21",
      "delay_min": 0.0,
      "status": "en_hora"
    },
    {
      "trip_id": "1090S76514C5",
      "route_id": "10T0017C5",
      "train_name": "C5",
      "headsign": "Madrid-Atocha Cercanías",
      "origin": "Móstoles-El Soto",
      "scheduled_time": "19:24",
      "estimated_time": "19:24",
      "delay_min": 0.0,
      "status": "en_hora"
    },
    {
      "trip_id": "1090S76505C5",
      "route_id": "10T0018C5",
      "train_name": "C5",
      "headsign": "Móstoles-El Soto",
      "origin": "Madrid-Atocha Cercanías",
      "scheduled_time": "19:31",
      "estimated_time": "19:31",
      "delay_min": 0.0,
      "status": "en_hora"
    },
    {
      "trip_id": "1090S76516C5",
      "route_id": "10T0017C5",
      "train_name": "C5",
      "headsign": "Madrid-Atocha Cercanías",
      "origin": "Móstoles-El Soto",
      "scheduled_time": "19:34",
      "estimated_time": "19:34",
      "delay_min": 0.0,
      "status": "en_hora"
    },
    {
      "trip_id": "1090S76507C5",
      "route_id": "10T0018C5",
      "train_name": "C5",
      "headsign": "Móstoles-El Soto",
      "origin": "Madrid-Atocha Cercanías",
      "scheduled_time": "19:41",
      "estimated_time": "19:41",
      "delay_min": 0.0,
      "status": "en_hora"
    },
    {
      "trip_id": "1090S76518C5",
      "route_id": "10T0017C5",
      "train_name": "C5",
      "headsign": "Madrid-Atocha Cercanías",
      "origin": "Móstoles-El Soto",
      "scheduled_time": "19:44",
      "estimated_time": "19:44",
      "delay_min": 0.0,
      "status": "en_hora"
    },
    {
      "trip_id": "1090S76509C5",
      "route_id": "10T0018C5",
      "train_name": "C5",
      "headsign": "Móstoles-El Soto",
      "origin": "Madrid-Atocha Cercanías",
      "scheduled_time": "19:51",
      "estimated_time": "19:51",
      "delay_min": 0.0,
      "status": "en_hora"
    },
    {
      "trip_id": "1090S76520C5",
      "route_id": "10T0017C5",
      "train_name": "C5",
      "headsign": "Madrid-Atocha Cercanías",
      "origin": "Móstoles-El Soto",
      "scheduled_time": "19:54",
      "estimated_time": "19:54",
      "delay_min": 0.0,
      "status": "en_hora"
    }
  ]
}