{
  "station_id": "51405",
  "name": "Cádiz",
  "generated_at": "2026-03-31T12:00:27+02:00",
  "arrivals": [
    {
      "trip_id": "3186M23216C1",
      "route_id": "31T0002C1",
      "train_name": "C1",
      "headsign": "Cádiz",
      "origin": "Jerez De La Frontera",
      "scheduled_time": "12:04",
      "estimated_time": "12:04",
      "delay_min": 0.0,
      "status": "en_hora"
    },
    {
      "trip_id": "3186M23219C1",
      "route_id": "31T0001C1",
      "train_name": "C1",
      "headsign": "Aeropuerto De Jerez",
      "origin": "Cádiz",
      "scheduled_time": "12:09",
      "estimated_time": "12:09",
      "delay_min": 0.0,
      "status": "en_hora"
    },
    {
      "trip_id": "3186M23434T1",
      "route_id": "31T0006T1",
      "train_name": "T1",
      "headsign": "Cádiz",
      "origin": "Pelagatos",
      "scheduled_time": "12:41",
      "estimated_time": "12:41",
      "delay_min": 0.0,
      "status": "en_hora"
    },
    {
      "trip_id": "3186M23435T1",
      "route_id": "31T0005T1",
      "train_name": "T1",
      "headsign": "Pelagatos",
      "origin": "Cádiz",
      "scheduled_time": "13:00",
      "estimated_time": "13:00",
      "delay_min": 0.0,
      "status": "en_hora"
    }
  ]
}