{
  "station_id": "51454",
  "name": "Alameda Solano",
  "generated_at": "2026-04-04T08:55:10+02:00",
  "arrivals": [
    {
      "trip_id": "3190S23425T1",
      "route_id": "31T0005T1",
      "train_name": "T1",
      "headsign": "Pelagatos",
      "origin": "Cádiz",
      "scheduled_time": "08:59",
      "estimated_time": "08:59",
      "delay_min": 0.0,
      "status": "en_hora"
    },
    {
      "trip_id": "3190S23430T1",
      "route_id": "31T0006T1",
      "train_name": "T1",
      "headsign": "Cádiz",
      "origin": "Pelagatos",
      "scheduled_time": "09:49",
      "estimated_time": "09:49",
      "delay_min": 0.0,
      "status": "en_hora"
    },
    {
      "trip_id": "3190S23427T1",
      "route_id": "31T0005T1",
      "train_name": "T1",
      "headsign": "Pelagatos",
      "origin": "Cádiz",
      "scheduled_time": "09:55",
      "estimated_time": "09:55",
      "delay_min": 0.0,
      "status": "en_hora"
    }
  ]
}