{
  "station_id": "54513",
  "name": "Carvajal",
  "generated_at": "2026-04-03T02:55:12+02:00",
  "arrivals": [
    {
      "trip_id": "3289V36322C1",
      "route_id": "32T0002C1",
      "train_name": "C1",
      "headsign": "Málaga-Centro Alameda",
      "origin": "Fuengirola",
      "scheduled_time": "03:06",
      "estimated_time": "03:06",
      "delay_min": 0.0,
      "status": "en_hora"
    },
    {
      "trip_id": "3289V36325C1",
      "route_id": "32T0001C1",
      "train_name": "C1",
      "headsign": "Fuengirola",
      "origin": "Málaga-Centro Alameda",
      "scheduled_time": "03:07",
      "estimated_time": "03:07",
      "delay_min": 0.0,
      "status": "en_hora"
    },
    {
      "trip_id": "3289V36324C1",
      "route_id": "32T0002C1",
      "train_name": "C1",
      "headsign": "Málaga-Centro Alameda",
      "origin": "Fuengirola",
      "scheduled_time": "03:26",
      "estimated_time": "03:26",
      "delay_min": 0.0,
      "status": "en_hora"
    },
    {
      "trip_id": "3289V36327C1",
      "route_id": "32T0001C1",
      "train_name": "C1",
      "headsign": "Fuengirola",
      "origin": "Málaga-Centro Alameda",
      "scheduled_time": "03:27",
      "estimated_time": "03:27",
      "delay_min": 0.0,
      "status": "en_hora"
    },
    {
      "trip_id": "3289V36326C1",
      "route_id": "32T0002C1",
      "train_name": "C1",
      "headsign": "Málaga-Centro Alameda",
      "origin": "Fuengirola",
      "scheduled_time": "03:46",
      "estimated_time": "03:46",
      "delay_min": 0.0,
      "status": "en_hora"
    }
  ]
}