{
  "station_id": "71100",
  "name": "Zaragoza-Miraflores",
  "generated_at": "2026-04-03T16:55:11+02:00",
  "arrivals": [
    {
      "trip_id": "7089V18515C1",
      "route_id": "70T0002C1",
      "train_name": "C1",
      "headsign": "Zaragoza Delicias",
      "origin": "Zaragoza-Miraflores",
      "scheduled_time": "16:58",
      "estimated_time": "16:58",
      "delay_min": 0.0,
      "status": "en_hora"
    },
    {
      "trip_id": "7089V15657C1",
      "route_id": "70T0002C1",
      "train_name": "C1",
      "headsign": "Zaragoza Delicias",
      "origin": "Zaragoza-Miraflores",
      "scheduled_time": "17:17",
      "estimated_time": "17:17",
      "delay_min": 0.0,
      "status": "en_hora"
    },
    {
      "trip_id": "7089V18076C1",
      "route_id": "70T0001C1",
      "train_name": "C1",
      "headsign": "Zaragoza-Miraflores",
      "origin": "Utebo",
      "scheduled_time": "17:20",
      "estimated_time": "17:20",
      "delay_min": 0.0,
      "status": "en_hora"
    },
    {
      "trip_id": "7089V18075C1",
      "route_id": "70T0002C1",
      "train_name": "C1",
      "headsign": "Casetas",
      "origin": "Zaragoza-Miraflores",
      "scheduled_time": "17:32",
      "estimated_time": "17:32",
      "delay_min": 0.0,
      "status": "en_hora"
    },
    {
      "trip_id": "7089V31526C1",
      "route_id": "70T0001C1",
      "train_name": "C1",
      "headsign": "Zaragoza-Miraflores",
      "origin": "Casetas",
      "scheduled_time": "17:43",
      "estimated_time": "17:43",
      "delay_min": 0.0,
      "status": "en_hora"
    },
    {
      "trip_id": "7089V31531C1",
      "route_id": "70T0002C1",
      "train_name": "C1",
      "headsign": "Casetas",
      "origin": "Zaragoza-Miraflores",
      "scheduled_time": "17:48",
      "estimated_time": "17:48",
      "delay_min": 0.0,
      "status": "en_hora"
    }
  ]
}