{
  "station_id": "72508",
  "name": "Santa Perpètua De Mogoda-Riera De Caldes",
  "generated_at": "2026-04-04T13:55:13+02:00",
  "arrivals": [
    {
      "trip_id": "5190S78648R8",
      "route_id": "51T0024R8",
      "train_name": "R8",
      "headsign": "Rubí Can Vallhonrat",
      "origin": "Granollers-Centre",
      "scheduled_time": "14:44",
      "estimated_time": "14:44",
      "delay_min": 0.0,
      "status": "en_hora"
    },
    {
      "trip_id": "5190S78616R8",
      "route_id": "51T0023R8",
      "train_name": "R8",
      "headsign": "Granollers-Centre",
      "origin": "Rubí Can Vallhonrat",
      "scheduled_time": "14:54",
      "estimated_time": "14:54",
      "delay_min": 0.0,
      "status": "en_hora"
    }
  ]
}