{
  "station_id": "77105",
  "name": "Centelles",
  "generated_at": "2026-04-04T19:55:13+02:00",
  "arrivals": [
    {
      "trip_id": "5190S77331R3",
      "route_id": "51T0040R3",
      "train_name": "R3",
      "headsign": "Vic",
      "origin": "La Garriga",
      "scheduled_time": "20:02",
      "estimated_time": "20:02",
      "delay_min": 0.0,
      "status": "en_hora"
    },
    {
      "trip_id": "5190S87103R3",
      "route_id": "51T0133R3",
      "train_name": "R3",
      "headsign": "Centelles",
      "origin": "Fabra I Puig",
      "scheduled_time": "20:16",
      "estimated_time": "20:16",
      "delay_min": 0.0,
      "status": "en_hora"
    },
    {
      "trip_id": "5190S87097R3",
      "route_id": "51T0133R3",
      "train_name": "R3",
      "headsign": "Centelles",
      "origin": "Fabra I Puig",
      "scheduled_time": "20:19",
      "estimated_time": "20:19",
      "delay_min": 0.0,
      "status": "en_hora"
    },
    {
      "trip_id": "5190S88048R3",
      "route_id": "51T0134R3",
      "train_name": "R3",
      "headsign": "Fabra I Puig",
      "origin": "Centelles",
      "scheduled_time": "20:20",
      "estimated_time": "20:20",
      "delay_min": 0.0,
      "status": "en_hora"
    },
    {
      "trip_id": "5190S87107R3",
      "route_id": "51T0133R3",
      "train_name": "R3",
      "headsign": "Centelles",
      "origin": "Fabra I Puig",
      "scheduled_time": "20:46",
      "estimated_time": "20:46",
      "delay_min": 0.0,
      "status": "en_hora"
    },
    {
      "trip_id": "5190S87101R3",
      "route_id": "51T0133R3",
      "train_name": "R3",
      "headsign": "Centelles",
      "origin": "Fabra I Puig",
      "scheduled_time": "20:49",
      "estimated_time": "20:49",
      "delay_min": 0.0,
      "status": "en_hora"
    },
    {
      "trip_id": "5190S88049R3",
      "route_id": "51T0134R3",
      "train_name": "R3",
      "headsign": "Fabra I Puig",
      "origin": "Centelles",
      "scheduled_time": "20:50",
      "estimated_time": "20:50",
      "delay_min": 0.0,
      "status": "en_hora"
    }
  ]
}