{
  "station_id": "79106",
  "name": "Riells I Viabrea-Breda",
  "generated_at": "2026-04-02T06:55:13+02:00",
  "arrivals": [
    {
      "trip_id": "5188J15900R11",
      "route_id": "51T0094R11",
      "train_name": "R11",
      "headsign": "Portbou",
      "origin": "Barcelona-Sants",
      "scheduled_time": "07:11",
      "estimated_time": "07:11",
      "delay_min": 0.0,
      "status": "en_hora"
    },
    {
      "trip_id": "5188J28476R2",
      "route_id": "51T0014R2",
      "train_name": "R2",
      "headsign": "Castelldefels",
      "origin": "Maçanet-Massanes",
      "scheduled_time": "07:14",
      "estimated_time": "07:14",
      "delay_min": 0.0,
      "status": "en_hora"
    }
  ]
}