{
  "station_id": "79408",
  "name": "Ocata",
  "generated_at": "2026-04-03T22:55:13+02:00",
  "arrivals": [
    {
      "trip_id": "5189V25691R1",
      "route_id": "51T0001R1",
      "train_name": "R1",
      "headsign": "Mataró",
      "origin": "L'hospitalet De Llobregat",
      "scheduled_time": "22:59",
      "estimated_time": "22:59",
      "delay_min": 0.0,
      "status": "en_hora"
    },
    {
      "trip_id": "5189V25693R1",
      "route_id": "51T0001R1",
      "train_name": "R1",
      "headsign": "Mataró",
      "origin": "L'hospitalet De Llobregat",
      "scheduled_time": "23:29",
      "estimated_time": "23:29",
      "delay_min": 0.0,
      "status": "en_hora"
    }
  ]
}