{
  "station_id": "31412",
  "name": "A Coruña",
  "generated_at": "2026-04-01T11:30:12+02:00",
  "arrivals": [
    {
      "trip_id": "1252612026-04-01",
      "route_id": "2230831412VRR",
      "train_name": "REGIONAL 12526",
      "headsign": "A Coruña",
      "origin": "Vigo Guixar",
      "scheduled_time": "11:35",
      "estimated_time": "11:52",
      "delay_min": 17.0,
      "status": "retraso_alto"
    },
    {
      "trip_id": "0912312026-03-31",
      "route_id": "3141208223VRX",
      "train_name": "MD 09123",
      "headsign": "Vigo Urzaiz",
      "origin": "A Coruña",
      "scheduled_time": "12:00",
      "estimated_time": "12:00",
      "delay_min": 0.0,
      "status": "en_hora"
    },
    {
      "trip_id": "0911212026-03-31",
      "route_id": "0822331412VRX",
      "train_name": "MD 09112",
      "headsign": "A Coruña",
      "origin": "Vigo Urzaiz",
      "scheduled_time": "12:04",
      "estimated_time": "12:28",
      "delay_min": 24.0,
      "status": "retraso_alto"
    },
    {
      "trip_id": "0429512026-03-31",
      "route_id": "1700031412LC112",
      "train_name": "AVLO 04295",
      "headsign": "A Coruña",
      "origin": "Madrid-Chamartín-Clara Campoamor",
      "scheduled_time": "12:27",
      "estimated_time": "12:24",
      "delay_min": -3.0,
      "status": "en_hora"
    },
    {
      "trip_id": "3429512026-03-31",
      "route_id": "2210031412AV008",
      "train_name": "AVANT 34295",
      "headsign": "A Coruña",
      "origin": "Ourense",
      "scheduled_time": "12:27",
      "estimated_time": "12:27",
      "delay_min": 0.0,
      "status": "en_hora"
    }
  ]
}