{
  "station_id": "50500",
  "name": "Cordoba",
  "generated_at": "2026-03-30T18:00:08",
  "arrivals": [
    {
      "trip_id": "0817512026-03-30",
      "route_id": "5100354413AV008",
      "train_name": "AVANT 08175",
      "headsign": "",
      "origin": "Sevilla-Santa Justa",
      "scheduled_time": "18:04",
      "estimated_time": "18:00",
      "delay_min": -4.0,
      "status": "en_hora"
    },
    {
      "trip_id": "0236012026-03-29",
      "route_id": "6000051003AV006",
      "train_name": "AVE 02360",
      "headsign": "",
      "origin": "Madrid Pta.Atocha - Almudena Grandes",
      "scheduled_time": "18:10",
      "estimated_time": "18:17",
      "delay_min": 7.0,
      "status": "retraso_alto"
    },
    {
      "trip_id": "0857512026-03-29",
      "route_id": "0500051003AV008",
      "train_name": "AVANT 08575",
      "headsign": "",
      "origin": "Granada",
      "scheduled_time": "18:13",
      "estimated_time": "18:21",
      "delay_min": 8.0,
      "status": "retraso_alto"
    },
    {
      "trip_id": "1324112026-03-29",
      "route_id": "5050250413VRN",
      "train_name": "PROXIMDAD 13241",
      "headsign": "",
      "origin": "Villarrubia de Cordoba",
      "scheduled_time": "18:27",
      "estimated_time": "18:27",
      "delay_min": 0.0,
      "status": "en_hora"
    },
    {
      "trip_id": "0236612026-03-29",
      "route_id": "6000056312GL023",
      "train_name": "ALVIA 02366",
      "headsign": "",
      "origin": "Madrid Pta.Atocha - Almudena Grandes",
      "scheduled_time": "18:33",
      "estimated_time": "18:35",
      "delay_min": 2.0,
      "status": "retraso_leve"
    },
    {
      "trip_id": "0236622026-03-29",
      "route_id": "6000005000GL023",
      "train_name": "ALVIA 02366",
      "headsign": "",
      "origin": "Madrid Pta.Atocha - Almudena Grandes",
      "scheduled_time": "18:33",
      "estimated_time": "18:35",
      "delay_min": 2.0,
      "status": "retraso_leve"
    },
    {
      "trip_id": "0217112026-03-29",
      "route_id": "5100360000AV006",
      "train_name": "AVE 02171",
      "headsign": "",
      "origin": "Sevilla-Santa Justa",
      "scheduled_time": "18:35",
      "estimated_time": "18:35",
      "delay_min": 0.0,
      "status": "en_hora"
    },
    {
      "trip_id": "1303512026-03-29",
      "route_id": "0310051405VRX",
      "train_name": "MD 13035",
      "headsign": "",
      "origin": "Jaen",
      "scheduled_time": "18:49",
      "estimated_time": "18:49",
      "delay_min": 0.0,
      "status": "en_hora"
    },
    {
      "trip_id": "3503512026-03-29",
      "route_id": "0310051405VRX",
      "train_name": "MD 35035",
      "headsign": "",
      "origin": "Jaen",
      "scheduled_time": "18:49",
      "estimated_time": "18:49",
      "delay_min": 0.0,
      "status": "en_hora"
    },
    {
      "trip_id": "3503522026-03-29",
      "route_id": "0310051405VRX",
      "train_name": "MD 35035",
      "headsign": "",
      "origin": "Jaen",
      "scheduled_time": "18:49",
      "estimated_time": "18:49",
      "delay_min": 0.0,
      "status": "en_hora"
    },
    {
      "trip_id": "3803512026-03-29",
      "route_id": "5040750506VRN",
      "train_name": "PROXIMDAD 38035",
      "headsign": "",
      "origin": "Villa del Rio",
      "scheduled_time": "18:49",
      "estimated_time": "18:49",
      "delay_min": 0.0,
      "status": "en_hora"
    }
  ]
}