{
  "station_id": "79309",
  "name": "Figueres",
  "generated_at": "2026-04-03T21:55:02+02:00",
  "arrivals": [
    {
      "trip_id": "1573612026-04-02",
      "route_id": "7180179309VRX",
      "train_name": "MD 15736",
      "headsign": "Figueres",
      "origin": "Barcelona-Sants",
      "scheduled_time": "22:10",
      "estimated_time": "22:28",
      "delay_min": 18.0,
      "status": "retraso_alto"
    },
    {
      "trip_id": "1573822026-04-02",
      "route_id": "7180179309VRX",
      "train_name": "MD 15738",
      "headsign": "Figueres",
      "origin": "Barcelona-Sants",
      "scheduled_time": "22:43",
      "estimated_time": "22:57",
      "delay_min": 14.0,
      "status": "retraso_alto"
    }
  ]
}